server.py
mcp_email_client-0.1.5.dist-info/METADATA
mcp_email_client-0.1.5.dist-info/WHEEL
mcp_email_client-0.1.5.dist-info/entry_points.txt
mcp_email_client-0.1.5.dist-info/top_level.txt
mcp_email_client-0.1.5.dist-info/RECORD
