Metadata-Version: 2.4
Name: mcp-email-client
Version: 0.1.5
Summary: A Model Context Protocol (MCP) server for sending and receiving emails, supporting IMAP/SMTP, with display name, reply, robust error handling, and full attachment support.
Author-email: 0xFFLR <chnwine@qq.com>
Requires-Python: >=3.10
Requires-Dist: fastmcp>=2.10.5
